{
    "class": "02958343",
    "model": "7478183ebde9c6c2afe717997470b28d",
    "remove_doubles": true,
    "edge_split": true,
    "denoise": true,
    "camera_angle_x": 0.6911112070083618,
    "scale_factor": 2.6457407150709398,
    "hdri_file": "/data/IndoorHDRDataset2018/9C4A7452-ff2e2a8144.exr",
    "center_offset": [
        0.0,
        0.0,
        1.862645149230957e-09
    ],
    "lights": [],
    "frames": [
        {
            "file_path": "/data/shapenet_blender/all_50_random/02958343/7478183ebde9c6c2afe717997470b28d/r_0",
            "rotation": 0.12566370614359174,
            "transform_matrix": [
                [
                    -0.9996612071990967,
                    0.0027895509265363216,
                    -0.025881288573145866,
                    -0.10433080792427063
                ],
                [
                    -0.026031186804175377,
                    -0.10712557286024094,
                    0.993904709815979,
                    4.006557941436768
                ],
                [
                    0.0,
                    0.9942415952682495,
                    0.10716187953948975,
                    0.4319833517074585
                ],
                [
                    0.0,
                    0.0,
                    0.0,
                    1.0
                ]
            ]
        },
        {
            "file_path": "/data/shapenet_blender/all_50_random/02958343/7478183ebde9c6c2afe717997470b28d/r_1",
            "rotation": 0.12566370614359174,
            "transform_matrix": [
                [
                    0.6983665227890015,
                    -0.24070636928081512,
                    0.6740508675575256,
                    2.7171859741210938
                ],
                [
                    0.7157403230667114,
                    0.2348634898662567,
                    -0.6576890349388123,
                    -2.6512293815612793
                ],
                [
                    0.0,
                    0.9417533874511719,
                    0.33630406856536865,
                    1.3556851148605347
                ],
                [
                    0.0,
                    0.0,
                    0.0,
                    1.0
                ]
            ]
        },
        {
            "file_path": "/data/shapenet_blender/all_50_random/02958343/7478183ebde9c6c2afe717997470b28d/r_2",
            "rotation": 0.12566370614359174,
            "transform_matrix": [
                [
                    -0.1241571307182312,
                    0.1594981551170349,
                    0.9793596863746643,
                    3.947925090789795
                ],
                [
                    0.9922626614570618,
                    0.019957248121500015,
                    0.12254264205694199,
                    0.4939851760864258
                ],
                [
                    1.862645149230957e-09,
                    0.9869964718818665,
                    -0.1607418805360794,
                    -0.6479712724685669
                ],
                [
                    0.0,
                    0.0,
                    0.0,
                    1.0
                ]
            ]
        },
        {
            "file_path": "/data/shapenet_blender/all_50_random/02958343/7478183ebde9c6c2afe717997470b28d/r_3",
            "rotation": 0.12566370614359174,
            "transform_matrix": [
                [
                    0.9797128438949585,
                    0.16947738826274872,
                    0.1069594994187355,
                    0.4311675429344177
                ],
                [
                    0.20040690898895264,
                    -0.8285102248191833,
                    -0.5228841304779053,
                    -2.1078133583068848
                ],
                [
                    0.0,
                    0.5337116122245789,
                    -0.8456664681434631,
                    -3.4089906215667725
                ],
                [
                    0.0,
                    0.0,
                    0.0,
                    1.0
                ]
            ]
        },
        {
            "file_path": "/data/shapenet_blender/all_50_random/02958343/7478183ebde9c6c2afe717997470b28d/r_4",
            "rotation": 0.12566370614359174,
            "transform_matrix": [
                [
                    0.8720768690109253,
                    -0.3595462441444397,
                    -0.33197665214538574,
                    -1.338240623474121
                ],
                [
                    -0.4893690049648285,
                    -0.6407270431518555,
                    -0.5915968418121338,
                    -2.384803056716919
                ],
                [
                    1.4901161193847656e-08,
                    0.6783769726753235,
                    -0.7347139716148376,
                    -2.961726665496826
                ],
                [
                    0.0,
                    0.0,
                    0.0,
                    1.0
                ]
            ]
        },
        {
            "file_path": "/data/shapenet_blender/all_50_random/02958343/7478183ebde9c6c2afe717997470b28d/r_5",
            "rotation": 0.12566370614359174,
            "transform_matrix": [
                [
                    0.9787718653678894,
                    0.006201418116688728,
                    -0.2048589438199997,
                    -0.825812816619873
                ],
                [
                    -0.20495279133319855,
                    0.02961547300219536,
                    -0.9783236980438232,
                    -3.943748950958252
                ],
                [
                    0.0,
                    0.9995421171188354,
                    0.03025778941810131,
                    0.12197305262088776
                ],
                [
                    0.0,
                    0.0,
                    0.0,
                    1.0
                ]
            ]
        },
        {
            "file_path": "/data/shapenet_blender/all_50_random/02958343/7478183ebde9c6c2afe717997470b28d/r_6",
            "rotation": 0.12566370614359174,
            "transform_matrix": [
                [
                    0.257920503616333,
                    -0.47827112674713135,
                    0.8394842147827148,
                    3.3840692043304443
                ],
                [
                    0.966166079044342,
                    0.12767571210861206,
                    -0.2241024672985077,
                    -0.9033859372138977
                ],
                [
                    0.0,
                    0.86888188123703,
                    0.4950195252895355,
                    1.9954875707626343
                ],
                [
                    0.0,
                    0.0,
                    0.0,
                    1.0
                ]
            ]
        },
        {
            "file_path": "/data/shapenet_blender/all_50_random/02958343/7478183ebde9c6c2afe717997470b28d/r_7",
            "rotation": 0.12566370614359174,
            "transform_matrix": [
                [
                    0.9657578468322754,
                    -0.20297107100486755,
                    -0.16160032153129578,
                    -0.6514317989349365
                ],
                [
                    -0.259445458650589,
                    -0.7555379867553711,
                    -0.6015398502349854,
                    -2.4248850345611572
                ],
                [
                    7.450581485102248e-09,
                    0.6228682398796082,
                    -0.7823265790939331,
                    -3.1536595821380615
                ],
                [
                    0.0,
                    0.0,
                    0.0,
                    1.0
                ]
            ]
        },
        {
            "file_path": "/data/shapenet_blender/all_50_random/02958343/7478183ebde9c6c2afe717997470b28d/r_8",
            "rotation": 0.12566370614359174,
            "transform_matrix": [
                [
                    0.4291120767593384,
                    -0.48424771428108215,
                    0.7624742388725281,
                    3.07363224029541
                ],
                [
                    0.9032512903213501,
                    0.23005394637584686,
                    -0.36223238706588745,
                    -1.4602055549621582
                ],
                [
                    0.0,
                    0.8441442251205444,
                    0.5361161231994629,
                    2.161153554916382
                ],
                [
                    0.0,
                    0.0,
                    0.0,
                    1.0
                ]
            ]
        },
        {
            "file_path": "/data/shapenet_blender/all_50_random/02958343/7478183ebde9c6c2afe717997470b28d/r_9",
            "rotation": 0.12566370614359174,
            "transform_matrix": [
                [
                    0.683128297328949,
                    -0.30798426270484924,
                    -0.6621792316436768,
                    -2.669329881668091
                ],
                [
                    -0.7302983403205872,
                    -0.2880915403366089,
                    -0.6194090247154236,
                    -2.496917486190796
                ],
                [
                    0.0,
                    0.9067242741584778,
                    -0.4217239022254944,
                    -1.7000232934951782
                ],
                [
                    0.0,
                    0.0,
                    0.0,
                    1.0
                ]
            ]
        },
        {
            "file_path": "/data/shapenet_blender/all_50_random/02958343/7478183ebde9c6c2afe717997470b28d/r_10",
            "rotation": 0.12566370614359174,
            "transform_matrix": [
                [
                    0.9317399263381958,
                    0.29111605882644653,
                    0.21705332398414612,
                    0.8749699592590332
                ],
                [
                    0.36312630772590637,
                    -0.746969997882843,
                    -0.5569336414337158,
                    -2.2450714111328125
                ],
                [
                    0.0,
                    0.5977350473403931,
                    -0.8016936182975769,
                    -3.2317304611206055
                ],
                [
                    0.0,
                    0.0,
                    0.0,
                    1.0
                ]
            ]
        },
        {
            "file_path": "/data/shapenet_blender/all_50_random/02958343/7478183ebde9c6c2afe717997470b28d/r_11",
            "rotation": 0.12566370614359174,
            "transform_matrix": [
                [
                    -0.4539117217063904,
                    0.27970588207244873,
                    0.8460074663162231,
                    3.410365343093872
                ],
                [
                    0.8910466432571411,
                    0.14248612523078918,
                    0.43096813559532166,
                    1.737288236618042
                ],
                [
                    -7.450580596923828e-09,
                    0.9494536519050598,
                    -0.31390711665153503,
                    -1.2654001712799072
                ],
                [
                    0.0,
                    0.0,
                    0.0,
                    1.0
                ]
            ]
        },
        {
            "file_path": "/data/shapenet_blender/all_50_random/02958343/7478183ebde9c6c2afe717997470b28d/r_12",
            "rotation": 0.12566370614359174,
            "transform_matrix": [
                [
                    -0.887157142162323,
                    -0.03258662670850754,
                    0.4603152871131897,
                    1.8555903434753418
                ],
                [
                    0.46146732568740845,
                    -0.06264681369066238,
                    0.8849424123764038,
                    3.567317247390747
                ],
                [
                    -1.862645149230957e-09,
                    0.9975034594535828,
                    0.0706152394413948,
                    0.28465917706489563
                ],
                [
                    0.0,
                    0.0,
                    0.0,
                    1.0
                ]
            ]
        },
        {
            "file_path": "/data/shapenet_blender/all_50_random/02958343/7478183ebde9c6c2afe717997470b28d/r_13",
            "rotation": 0.12566370614359174,
            "transform_matrix": [
                [
                    -0.9510056972503662,
                    0.057600002735853195,
                    -0.3037603795528412,
                    -1.2244971990585327
                ],
                [
                    -0.3091732859611511,
                    -0.17717549204826355,
                    0.9343557953834534,
                    3.7665085792541504
                ],
                [
                    0.0,
                    0.9824922680854797,
                    0.1863032877445221,
                    0.7510125637054443
                ],
                [
                    0.0,
                    0.0,
                    0.0,
                    1.0
                ]
            ]
        },
        {
            "file_path": "/data/shapenet_blender/all_50_random/02958343/7478183ebde9c6c2afe717997470b28d/r_14",
            "rotation": 0.12566370614359174,
            "transform_matrix": [
                [
                    -0.7525143623352051,
                    0.06569094955921173,
                    -0.6552914977073669,
                    -2.6415646076202393
                ],
                [
                    -0.6585759520530701,
                    -0.07506101578474045,
                    0.7487613558769226,
                    3.0183534622192383
                ],
                [
                    0.0,
                    0.9950127601623535,
                    0.09974697232246399,
                    0.40209290385246277
                ],
                [
                    0.0,
                    0.0,
                    0.0,
                    1.0
                ]
            ]
        },
        {
            "file_path": "/data/shapenet_blender/all_50_random/02958343/7478183ebde9c6c2afe717997470b28d/r_15",
            "rotation": 0.12566370614359174,
            "transform_matrix": [
                [
                    -0.5690430998802185,
                    0.4646870493888855,
                    -0.678421676158905,
                    -2.73480486869812
                ],
                [
                    -0.8223077058792114,
                    -0.3215669095516205,
                    0.46947285532951355,
                    1.892505407333374
                ],
                [
                    0.0,
                    0.8250215649604797,
                    0.5651012659072876,
                    2.2779958248138428
                ],
                [
                    0.0,
                    0.0,
                    0.0,
                    1.0
                ]
            ]
        },
        {
            "file_path": "/data/shapenet_blender/all_50_random/02958343/7478183ebde9c6c2afe717997470b28d/r_16",
            "rotation": 0.12566370614359174,
            "transform_matrix": [
                [
                    -0.04746808111667633,
                    -0.7302030324935913,
                    0.6815792322158813,
                    2.7475337982177734
                ],
                [
                    0.9988727569580078,
                    -0.03470044955611229,
                    0.03238976374268532,
                    0.13056731224060059
                ],
                [
                    1.862645371275562e-09,
                    0.6823484301567078,
                    0.7310270667076111,
                    2.946864366531372
                ],
                [
                    0.0,
                    0.0,
                    0.0,
                    1.0
                ]
            ]
        },
        {
            "file_path": "/data/shapenet_blender/all_50_random/02958343/7478183ebde9c6c2afe717997470b28d/r_17",
            "rotation": 0.12566370614359174,
            "transform_matrix": [
                [
                    -0.9586135745048523,
                    0.026725735515356064,
                    0.28345298767089844,
                    1.1426355838775635
                ],
                [
                    0.2847101092338562,
                    0.08998505026102066,
                    0.9543808698654175,
                    3.8472323417663574
                ],
                [
                    -1.8626450382086546e-09,
                    0.9955844879150391,
                    -0.09386997669935226,
                    -0.3784019649028778
                ],
                [
                    0.0,
                    0.0,
                    0.0,
                    1.0
                ]
            ]
        },
        {
            "file_path": "/data/shapenet_blender/all_50_random/02958343/7478183ebde9c6c2afe717997470b28d/r_18",
            "rotation": 0.12566370614359174,
            "transform_matrix": [
                [
                    0.43196403980255127,
                    -0.708979070186615,
                    -0.5574545860290527,
                    -2.247171640396118
                ],
                [
                    -0.9018908143043518,
                    -0.33956825733184814,
                    -0.26699501276016235,
                    -1.0762914419174194
                ],
                [
                    -1.4901161193847656e-08,
                    0.6180955171585083,
                    -0.7861029505729675,
                    -3.1688826084136963
                ],
                [
                    0.0,
                    0.0,
                    0.0,
                    1.0
                ]
            ]
        },
        {
            "file_path": "/data/shapenet_blender/all_50_random/02958343/7478183ebde9c6c2afe717997470b28d/r_19",
            "rotation": 0.12566370614359174,
            "transform_matrix": [
                [
                    -0.9732846617698669,
                    -0.000979050644673407,
                    -0.22959958016872406,
                    -0.9255455732345581
                ],
                [
                    -0.2296016663312912,
                    0.004150209482759237,
                    0.9732757806777954,
                    3.923400402069092
                ],
                [
                    5.8207653974573503e-11,
                    0.9999909400939941,
                    -0.004264126531779766,
                    -0.01718924567103386
                ],
                [
                    0.0,
                    0.0,
                    0.0,
                    1.0
                ]
            ]
        },
        {
            "file_path": "/data/shapenet_blender/all_50_random/02958343/7478183ebde9c6c2afe717997470b28d/r_20",
            "rotation": 0.12566370614359174,
            "transform_matrix": [
                [
                    -0.9561493992805481,
                    -0.056637272238731384,
                    -0.2873511016368866,
                    -1.1583493947982788
                ],
                [
                    -0.292879581451416,
                    0.1849008947610855,
                    0.9381008744239807,
                    3.7816054821014404
                ],
                [
                    0.0,
                    0.9811237454414368,
                    -0.19338077306747437,
                    -0.7795428037643433
                ],
                [
                    0.0,
                    0.0,
                    0.0,
                    1.0
                ]
            ]
        },
        {
            "file_path": "/data/shapenet_blender/all_50_random/02958343/7478183ebde9c6c2afe717997470b28d/r_21",
            "rotation": 0.12566370614359174,
            "transform_matrix": [
                [
                    -0.2913544476032257,
                    0.2861543297767639,
                    -0.9128133654594421,
                    -3.679668426513672
                ],
                [
                    -0.9566152691841125,
                    -0.08715347945690155,
                    0.27801379561424255,
                    1.1207094192504883
                ],
                [
                    -7.450581485102248e-09,
                    0.9542115926742554,
                    0.29913216829299927,
                    1.2058403491973877
                ],
                [
                    0.0,
                    0.0,
                    0.0,
                    1.0
                ]
            ]
        },
        {
            "file_path": "/data/shapenet_blender/all_50_random/02958343/7478183ebde9c6c2afe717997470b28d/r_22",
            "rotation": 0.12566370614359174,
            "transform_matrix": [
                [
                    0.9969659447669983,
                    0.007160780485719442,
                    0.07750976085662842,
                    0.3124518394470215
                ],
                [
                    0.07783983647823334,
                    -0.09171465784311295,
                    -0.9927383661270142,
                    -4.001856327056885
                ],
                [
                    -4.656613428188905e-10,
                    0.9957594871520996,
                    -0.0919937938451767,
                    -0.37083885073661804
                ],
                [
                    0.0,
                    0.0,
                    0.0,
                    1.0
                ]
            ]
        },
        {
            "file_path": "/data/shapenet_blender/all_50_random/02958343/7478183ebde9c6c2afe717997470b28d/r_23",
            "rotation": 0.12566370614359174,
            "transform_matrix": [
                [
                    -0.22743242979049683,
                    0.2739543914794922,
                    0.9344642162322998,
                    3.7669458389282227
                ],
                [
                    0.9737938046455383,
                    0.06398285180330276,
                    0.21824689209461212,
                    0.8797813653945923
                ],
                [
                    1.1175871783564162e-08,
                    0.9596118927001953,
                    -0.28132688999176025,
                    -1.1340649127960205
                ],
                [
                    0.0,
                    0.0,
                    0.0,
                    1.0
                ]
            ]
        },
        {
            "file_path": "/data/shapenet_blender/all_50_random/02958343/7478183ebde9c6c2afe717997470b28d/r_24",
            "rotation": 0.12566370614359174,
            "transform_matrix": [
                [
                    -0.4464588463306427,
                    0.3095710873603821,
                    -0.8395476341247559,
                    -3.384324789047241
                ],
                [
                    -0.8948042392730713,
                    -0.15445920825004578,
                    0.41888877749443054,
                    1.6885946989059448
                ],
                [
                    -1.4901162970204496e-08,
                    0.9382472038269043,
                    0.3459652364253998,
                    1.3946304321289062
                ],
                [
                    0.0,
                    0.0,
                    0.0,
                    1.0
                ]
            ]
        },
        {
            "file_path": "/data/shapenet_blender/all_50_random/02958343/7478183ebde9c6c2afe717997470b28d/r_25",
            "rotation": 0.12566370614359174,
            "transform_matrix": [
                [
                    -0.7565693855285645,
                    0.2860465347766876,
                    -0.5880306959152222,
                    -2.3704278469085693
                ],
                [
                    -0.6539134383201599,
                    -0.33095213770866394,
                    0.6803438663482666,
                    2.742554187774658
                ],
                [
                    -1.4901161193847656e-08,
                    0.8992485404014587,
                    0.43743789196014404,
                    1.7633686065673828
                ],
                [
                    0.0,
                    0.0,
                    0.0,
                    1.0
                ]
            ]
        },
        {
            "file_path": "/data/shapenet_blender/all_50_random/02958343/7478183ebde9c6c2afe717997470b28d/r_26",
            "rotation": 0.12566370614359174,
            "transform_matrix": [
                [
                    0.41801708936691284,
                    0.7841042876243591,
                    -0.45873987674713135,
                    -1.8492395877838135
                ],
                [
                    -0.9084391593933105,
                    0.36080455780029297,
                    -0.21108853816986084,
                    -0.850925087928772
                ],
                [
                    1.4901161193847656e-08,
                    0.5049757957458496,
                    0.8631334900856018,
                    3.4794023036956787
                ],
                [
                    0.0,
                    0.0,
                    0.0,
                    1.0
                ]
            ]
        },
        {
            "file_path": "/data/shapenet_blender/all_50_random/02958343/7478183ebde9c6c2afe717997470b28d/r_27",
            "rotation": 0.12566370614359174,
            "transform_matrix": [
                [
                    -0.9941409826278687,
                    -0.08209378272294998,
                    0.07031550258398056,
                    0.2834508717060089
                ],
                [
                    0.10809096693992615,
                    -0.7550380229949951,
                    0.6467101573944092,
                    2.6069719791412354
                ],
                [
                    -3.7252898543727042e-09,
                    0.6505215764045715,
                    0.7594878077507019,
                    3.0615932941436768
                ],
                [
                    0.0,
                    0.0,
                    0.0,
                    1.0
                ]
            ]
        },
        {
            "file_path": "/data/shapenet_blender/all_50_random/02958343/7478183ebde9c6c2afe717997470b28d/r_28",
            "rotation": 0.12566370614359174,
            "transform_matrix": [
                [
                    -0.37861916422843933,
                    0.4312467873096466,
                    -0.8189467191696167,
                    -3.3012797832489014
                ],
                [
                    -0.9255525469779968,
                    -0.1764117032289505,
                    0.33500954508781433,
                    1.3504667282104492
                ],
                [
                    1.4901161193847656e-08,
                    0.8848192095756531,
                    0.4659344255924225,
                    1.878241777420044
                ],
                [
                    0.0,
                    0.0,
                    0.0,
                    1.0
                ]
            ]
        },
        {
            "file_path": "/data/shapenet_blender/all_50_random/02958343/7478183ebde9c6c2afe717997470b28d/r_29",
            "rotation": 0.12566370614359174,
            "transform_matrix": [
                [
                    -0.9995289444923401,
                    0.012975011020898819,
                    0.027811899781227112,
                    0.112113356590271
                ],
                [
                    0.03068961761891842,
                    0.42258259654045105,
                    0.9058046340942383,
                    3.6514153480529785
                ],
                [
                    9.313225746154785e-10,
                    0.9062314629554749,
                    -0.42278173565864563,
                    -1.7042876482009888
                ],
                [
                    0.0,
                    0.0,
                    0.0,
                    1.0
                ]
            ]
        },
        {
            "file_path": "/data/shapenet_blender/all_50_random/02958343/7478183ebde9c6c2afe717997470b28d/r_30",
            "rotation": 0.12566370614359174,
            "transform_matrix": [
                [
                    -0.4245414733886719,
                    -0.45857706665992737,
                    0.780686616897583,
                    3.1470484733581543
                ],
                [
                    0.9054085612297058,
                    -0.2150244414806366,
                    0.3660599887371063,
                    1.475635051727295
                ],
                [
                    0.0,
                    0.8622478246688843,
                    0.5064863562583923,
                    2.0417118072509766
                ],
                [
                    0.0,
                    0.0,
                    0.0,
                    1.0
                ]
            ]
        },
        {
            "file_path": "/data/shapenet_blender/all_50_random/02958343/7478183ebde9c6c2afe717997470b28d/r_31",
            "rotation": 0.12566370614359174,
            "transform_matrix": [
                [
                    -0.9991405606269836,
                    -0.03619810938835144,
                    -0.02019980363547802,
                    -0.08142802119255066
                ],
                [
                    -0.041452813893556595,
                    0.8724859952926636,
                    0.48687756061553955,
                    1.962666392326355
                ],
                [
                    -1.862645149230957e-09,
                    0.48729658126831055,
                    -0.8732365965843201,
                    -3.520129442214966
                ],
                [
                    0.0,
                    0.0,
                    0.0,
                    1.0
                ]
            ]
        },
        {
            "file_path": "/data/shapenet_blender/all_50_random/02958343/7478183ebde9c6c2afe717997470b28d/r_32",
            "rotation": 0.12566370614359174,
            "transform_matrix": [
                [
                    0.9684667587280273,
                    -0.08550330251455307,
                    -0.2340112030506134,
                    -0.9433292150497437
                ],
                [
                    -0.2491426318883896,
                    -0.33236828446388245,
                    -0.9096479415893555,
                    -3.666907787322998
                ],
                [
                    0.0,
                    0.9392659068107605,
                    -0.34319019317626953,
                    -1.3834437131881714
                ],
                [
                    0.0,
                    0.0,
                    0.0,
                    1.0
                ]
            ]
        },
        {
            "file_path": "/data/shapenet_blender/all_50_random/02958343/7478183ebde9c6c2afe717997470b28d/r_33",
            "rotation": 0.12566370614359174,
            "transform_matrix": [
                [
                    -0.9354985356330872,
                    -0.010839508846402168,
                    -0.3531644642353058,
                    -1.4236515760421753
                ],
                [
                    -0.3533308207988739,
                    0.028699291869997978,
                    0.935058057308197,
                    3.7693397998809814
                ],
                [
                    0.0,
                    0.9995293021202087,
                    -0.030678074806928635,
                    -0.12366728484630585
                ],
                [
                    0.0,
                    0.0,
                    0.0,
                    1.0
                ]
            ]
        },
        {
            "file_path": "/data/shapenet_blender/all_50_random/02958343/7478183ebde9c6c2afe717997470b28d/r_34",
            "rotation": 0.12566370614359174,
            "transform_matrix": [
                [
                    -0.6981011033058167,
                    0.6288577318191528,
                    0.34233424067497253,
                    1.3799934387207031
                ],
                [
                    0.7159992456436157,
                    0.6131379008293152,
                    0.3337767720222473,
                    1.3454972505569458
                ],
                [
                    1.4901162970204496e-08,
                    0.47812092304229736,
                    -0.8782939910888672,
                    -3.5405163764953613
                ],
                [
                    0.0,
                    0.0,
                    0.0,
                    1.0
                ]
            ]
        },
        {
            "file_path": "/data/shapenet_blender/all_50_random/02958343/7478183ebde9c6c2afe717997470b28d/r_35",
            "rotation": 0.12566370614359174,
            "transform_matrix": [
                [
                    -0.16838710010051727,
                    -0.575809121131897,
                    -0.800055980682373,
                    -3.2251288890838623
                ],
                [
                    -0.9857209324836731,
                    0.09836337715387344,
                    0.13667063415050507,
                    0.5509369373321533
                ],
                [
                    7.450580596923828e-09,
                    0.8116454482078552,
                    -0.5841502547264099,
                    -2.3547849655151367
                ],
                [
                    0.0,
                    0.0,
                    0.0,
                    1.0
                ]
            ]
        },
        {
            "file_path": "/data/shapenet_blender/all_50_random/02958343/7478183ebde9c6c2afe717997470b28d/r_36",
            "rotation": 0.12566370614359174,
            "transform_matrix": [
                [
                    0.6681698560714722,
                    0.21718716621398926,
                    -0.7116029858589172,
                    -2.868563413619995
                ],
                [
                    -0.7440088391304016,
                    0.19504863023757935,
                    -0.6390672326087952,
                    -2.576162338256836
                ],
                [
                    -1.4901162970204496e-08,
                    0.9564442038536072,
                    0.29191482067108154,
                    1.1767462491989136
                ],
                [
                    0.0,
                    0.0,
                    0.0,
                    1.0
                ]
            ]
        },
        {
            "file_path": "/data/shapenet_blender/all_50_random/02958343/7478183ebde9c6c2afe717997470b28d/r_37",
            "rotation": 0.12566370614359174,
            "transform_matrix": [
                [
                    -0.17643749713897705,
                    0.5956067442893982,
                    -0.7836596369743347,
                    -3.1590332984924316
                ],
                [
                    -0.9843119382858276,
                    -0.10676225274801254,
                    0.14047065377235413,
                    0.5662553906440735
                ],
                [
                    0.0,
                    0.7961498498916626,
                    0.6050994992256165,
                    2.4392342567443848
                ],
                [
                    0.0,
                    0.0,
                    0.0,
                    1.0
                ]
            ]
        },
        {
            "file_path": "/data/shapenet_blender/all_50_random/02958343/7478183ebde9c6c2afe717997470b28d/r_38",
            "rotation": 0.12566370614359174,
            "transform_matrix": [
                [
                    -0.9977195262908936,
                    0.026320751756429672,
                    0.062153443694114685,
                    0.2505485415458679
                ],
                [
                    0.06749691069126129,
                    0.38906559348106384,
                    0.9187339544296265,
                    3.7035350799560547
                ],
                [
                    1.862645371275562e-09,
                    0.9208338856697083,
                    -0.38995492458343506,
                    -1.5719585418701172
                ],
                [
                    0.0,
                    0.0,
                    0.0,
                    1.0
                ]
            ]
        },
        {
            "file_path": "/data/shapenet_blender/all_50_random/02958343/7478183ebde9c6c2afe717997470b28d/r_39",
            "rotation": 0.12566370614359174,
            "transform_matrix": [
                [
                    0.9999315738677979,
                    0.010425997897982597,
                    -0.005308628547936678,
                    -0.021399766206741333
                ],
                [
                    -0.01169970165938139,
                    0.8910727500915527,
                    -0.45370951294898987,
                    -1.8289614915847778
                ],
                [
                    -4.656613428188905e-10,
                    0.4537404477596283,
                    0.8911338448524475,
                    3.592275381088257
                ],
                [
                    0.0,
                    0.0,
                    0.0,
                    1.0
                ]
            ]
        },
        {
            "file_path": "/data/shapenet_blender/all_50_random/02958343/7478183ebde9c6c2afe717997470b28d/r_40",
            "rotation": 0.12566370614359174,
            "transform_matrix": [
                [
                    0.9844567179679871,
                    -0.03161041438579559,
                    0.17275947332382202,
                    0.6964157223701477
                ],
                [
                    0.17562760412693024,
                    0.17718788981437683,
                    -0.9683797955513,
                    -3.9036638736724854
                ],
                [
                    0.0,
                    0.9836692214012146,
                    0.17998546361923218,
                    0.7255446314811707
                ],
                [
                    0.0,
                    0.0,
                    0.0,
                    1.0
                ]
            ]
        },
        {
            "file_path": "/data/shapenet_blender/all_50_random/02958343/7478183ebde9c6c2afe717997470b28d/r_41",
            "rotation": 0.12566370614359174,
            "transform_matrix": [
                [
                    0.11995589733123779,
                    -0.01534090656787157,
                    0.992660641670227,
                    4.001543045043945
                ],
                [
                    0.9927792549133301,
                    0.0018536169081926346,
                    -0.11994156986474991,
                    -0.4834999442100525
                ],
                [
                    -1.1641530794914701e-10,
                    0.9998806715011597,
                    0.015452486462891102,
                    0.062290966510772705
                ],
                [
                    0.0,
                    0.0,
                    0.0,
                    1.0
                ]
            ]
        },
        {
            "file_path": "/data/shapenet_blender/all_50_random/02958343/7478183ebde9c6c2afe717997470b28d/r_42",
            "rotation": 0.12566370614359174,
            "transform_matrix": [
                [
                    0.17563827335834503,
                    -0.5254401564598083,
                    0.8325045108795166,
                    3.3559329509735107
                ],
                [
                    0.9844548106193542,
                    0.0937446877360344,
                    -0.1485285609960556,
                    -0.5987377762794495
                ],
                [
                    0.0,
                    0.8456502556800842,
                    0.533737301826477,
                    2.151563882827759
                ],
                [
                    0.0,
                    0.0,
                    0.0,
                    1.0
                ]
            ]
        },
        {
            "file_path": "/data/shapenet_blender/all_50_random/02958343/7478183ebde9c6c2afe717997470b28d/r_43",
            "rotation": 0.12566370614359174,
            "transform_matrix": [
                [
                    0.8818154335021973,
                    0.3231704831123352,
                    0.3434564769268036,
                    1.3845173120498657
                ],
                [
                    0.4715946316719055,
                    -0.6042831540107727,
                    -0.6422151327133179,
                    -2.5888519287109375
                ],
                [
                    -1.4901159417490817e-08,
                    0.7282874584197998,
                    -0.685271680355072,
                    -2.762418508529663
                ],
                [
                    0.0,
                    0.0,
                    0.0,
                    1.0
                ]
            ]
        },
        {
            "file_path": "/data/shapenet_blender/all_50_random/02958343/7478183ebde9c6c2afe717997470b28d/r_44",
            "rotation": 0.12566370614359174,
            "transform_matrix": [
                [
                    -0.6593581438064575,
                    0.7391120791435242,
                    0.1376958042383194,
                    0.5550694465637207
                ],
                [
                    0.7518290281295776,
                    0.6482052803039551,
                    0.12075996398925781,
                    0.4867989420890808
                ],
                [
                    0.0,
                    0.18314780294895172,
                    -0.9830854535102844,
                    -3.9629437923431396
                ],
                [
                    0.0,
                    0.0,
                    0.0,
                    1.0
                ]
            ]
        },
        {
            "file_path": "/data/shapenet_blender/all_50_random/02958343/7478183ebde9c6c2afe717997470b28d/r_45",
            "rotation": 0.12566370614359174,
            "transform_matrix": [
                [
                    0.6131693720817566,
                    -0.5726014375686646,
                    -0.5441974997520447,
                    -2.193730354309082
                ],
                [
                    -0.7899515628814697,
                    -0.4444597363471985,
                    -0.42241227626800537,
                    -1.7027983665466309
                ],
                [
                    0.0,
                    0.6888998746871948,
                    -0.7248564958572388,
                    -2.921989917755127
                ],
                [
                    0.0,
                    0.0,
                    0.0,
                    1.0
                ]
            ]
        },
        {
            "file_path": "/data/shapenet_blender/all_50_random/02958343/7478183ebde9c6c2afe717997470b28d/r_46",
            "rotation": 0.12566370614359174,
            "transform_matrix": [
                [
                    0.9978979825973511,
                    -0.010752108879387379,
                    -0.06390673667192459,
                    -0.2576162815093994
                ],
                [
                    -0.06480493396520615,
                    -0.16556623578071594,
                    -0.9840671420097351,
                    -3.9669015407562256
                ],
                [
                    -9.313225746154785e-10,
                    0.9861400723457336,
                    -0.16591498255729675,
                    -0.6688246726989746
                ],
                [
                    0.0,
                    0.0,
                    0.0,
                    1.0
                ]
            ]
        },
        {
            "file_path": "/data/shapenet_blender/all_50_random/02958343/7478183ebde9c6c2afe717997470b28d/r_47",
            "rotation": 0.12566370614359174,
            "transform_matrix": [
                [
                    -0.016420921310782433,
                    -0.19715672731399536,
                    0.9802344441413879,
                    3.951451301574707
                ],
                [
                    0.9998652338981628,
                    -0.0032379317563027143,
                    0.016098521649837494,
                    0.06489521265029907
                ],
                [
                    2.3283064365386963e-10,
                    0.9803666472434998,
                    0.19718332588672638,
                    0.7948713898658752
                ],
                [
                    0.0,
                    0.0,
                    0.0,
                    1.0
                ]
            ]
        },
        {
            "file_path": "/data/shapenet_blender/all_50_random/02958343/7478183ebde9c6c2afe717997470b28d/r_48",
            "rotation": 0.12566370614359174,
            "transform_matrix": [
                [
                    0.368242472410202,
                    -0.04661445692181587,
                    0.9285603761672974,
                    3.7431468963623047
                ],
                [
                    0.9297297596931458,
                    0.018462808802723885,
                    -0.36777931451797485,
                    -1.482565999031067
                ],
                [
                    0.0,
                    0.9987422227859497,
                    0.050137635320425034,
                    0.20211128890514374
                ],
                [
                    0.0,
                    0.0,
                    0.0,
                    1.0
                ]
            ]
        },
        {
            "file_path": "/data/shapenet_blender/all_50_random/02958343/7478183ebde9c6c2afe717997470b28d/r_49",
            "rotation": 0.12566370614359174,
            "transform_matrix": [
                [
                    0.7605523467063904,
                    0.09706884622573853,
                    -0.6419795751571655,
                    -2.587902069091797
                ],
                [
                    -0.649276614189148,
                    0.11370492726564407,
                    -0.7520048022270203,
                    -3.0314278602600098
                ],
                [
                    0.0,
                    0.9887612462043762,
                    0.14950309693813324,
                    0.6026661992073059
                ],
                [
                    0.0,
                    0.0,
                    0.0,
                    1.0
                ]
            ]
        }
    ]
}