{
    "class": "02958343",
    "model": "cc7f51159a1a12fea7fd25564c2e888e",
    "remove_doubles": true,
    "edge_split": true,
    "denoise": true,
    "camera_angle_x": 0.6911112070083618,
    "scale_factor": 2.3786077490688324,
    "hdri_file": "/data/IndoorHDRDataset2018/9C4A4742-1d56d6a1cb.exr",
    "center_offset": [
        0.0,
        -3.725290298461914e-09,
        0.0
    ],
    "lights": [],
    "frames": [
        {
            "file_path": "/data/shapenet_blender/all_50_random/02958343/cc7f51159a1a12fea7fd25564c2e888e/r_0",
            "rotation": 0.12566370614359174,
            "transform_matrix": [
                [
                    -0.33411723375320435,
                    -0.40105071663856506,
                    -0.8529500961303711,
                    -3.438352108001709
                ],
                [
                    -0.9425315260887146,
                    0.14216814935207367,
                    0.3023615777492523,
                    1.2188585996627808
                ],
                [
                    0.0,
                    0.9049566388130188,
                    -0.42550376057624817,
                    -1.715260624885559
                ],
                [
                    0.0,
                    0.0,
                    0.0,
                    1.0
                ]
            ]
        },
        {
            "file_path": "/data/shapenet_blender/all_50_random/02958343/cc7f51159a1a12fea7fd25564c2e888e/r_1",
            "rotation": 0.12566370614359174,
            "transform_matrix": [
                [
                    -0.694753885269165,
                    -0.055439725518226624,
                    -0.7171078324317932,
                    -2.890753746032715
                ],
                [
                    -0.7192476391792297,
                    0.05355173721909523,
                    0.692686915397644,
                    2.7923099994659424
                ],
                [
                    0.0,
                    0.9970248937606812,
                    -0.07708017528057098,
                    -0.3107200860977173
                ],
                [
                    0.0,
                    0.0,
                    0.0,
                    1.0
                ]
            ]
        },
        {
            "file_path": "/data/shapenet_blender/all_50_random/02958343/cc7f51159a1a12fea7fd25564c2e888e/r_2",
            "rotation": 0.12566370614359174,
            "transform_matrix": [
                [
                    0.793134331703186,
                    0.47233301401138306,
                    0.3844989836215973,
                    1.5499651432037354
                ],
                [
                    0.6090468168258667,
                    -0.6150980591773987,
                    -0.5007157325744629,
                    -2.0184500217437744
                ],
                [
                    0.0,
                    0.6313127279281616,
                    -0.7755282521247864,
                    -3.1262545585632324
                ],
                [
                    0.0,
                    0.0,
                    0.0,
                    1.0
                ]
            ]
        },
        {
            "file_path": "/data/shapenet_blender/all_50_random/02958343/cc7f51159a1a12fea7fd25564c2e888e/r_3",
            "rotation": 0.12566370614359174,
            "transform_matrix": [
                [
                    -0.990155041217804,
                    -0.1094830334186554,
                    0.08721522986888885,
                    0.3515758514404297
                ],
                [
                    0.13997510075569153,
                    -0.7744603157043457,
                    0.6169425249099731,
                    2.4869749546051025
                ],
                [
                    -7.450580596923828e-09,
                    0.6230765581130981,
                    0.7821606993675232,
                    3.1529905796051025
                ],
                [
                    0.0,
                    0.0,
                    0.0,
                    1.0
                ]
            ]
        },
        {
            "file_path": "/data/shapenet_blender/all_50_random/02958343/cc7f51159a1a12fea7fd25564c2e888e/r_4",
            "rotation": 0.12566370614359174,
            "transform_matrix": [
                [
                    -0.7250717878341675,
                    0.2090972661972046,
                    -0.6561625003814697,
                    -2.645075798034668
                ],
                [
                    -0.6886733770370483,
                    -0.22014866769313812,
                    0.6908426284790039,
                    2.7848758697509766
                ],
                [
                    0.0,
                    0.9527921676635742,
                    0.3036232888698578,
                    1.2239447832107544
                ],
                [
                    0.0,
                    0.0,
                    0.0,
                    1.0
                ]
            ]
        },
        {
            "file_path": "/data/shapenet_blender/all_50_random/02958343/cc7f51159a1a12fea7fd25564c2e888e/r_5",
            "rotation": 0.12566370614359174,
            "transform_matrix": [
                [
                    0.18688827753067017,
                    -0.1967736780643463,
                    -0.9624723196029663,
                    -3.879849910736084
                ],
                [
                    -0.9823812246322632,
                    -0.03743423894047737,
                    -0.18310081958770752,
                    -0.7381030321121216
                ],
                [
                    3.725290298461914e-09,
                    0.9797340631484985,
                    -0.20030277967453003,
                    -0.8074463605880737
                ],
                [
                    0.0,
                    0.0,
                    0.0,
                    1.0
                ]
            ]
        },
        {
            "file_path": "/data/shapenet_blender/all_50_random/02958343/cc7f51159a1a12fea7fd25564c2e888e/r_6",
            "rotation": 0.12566370614359174,
            "transform_matrix": [
                [
                    -0.8168243169784546,
                    0.041537974029779434,
                    0.57538902759552,
                    2.319467544555664
                ],
                [
                    0.5768864750862122,
                    0.0588143952190876,
                    0.8147041201591492,
                    3.284177541732788
                ],
                [
                    0.0,
                    0.9974043965339661,
                    -0.07200371474027634,
                    -0.2902562916278839
                ],
                [
                    0.0,
                    0.0,
                    0.0,
                    1.0
                ]
            ]
        },
        {
            "file_path": "/data/shapenet_blender/all_50_random/02958343/cc7f51159a1a12fea7fd25564c2e888e/r_7",
            "rotation": 0.12566370614359174,
            "transform_matrix": [
                [
                    0.8751258254051208,
                    -0.020919330418109894,
                    0.4834432601928711,
                    1.9488221406936646
                ],
                [
                    0.4838956594467163,
                    0.03783262521028519,
                    -0.8743075728416443,
                    -3.524446487426758
                ],
                [
                    1.862645371275562e-09,
                    0.9990650415420532,
                    0.04323108121752739,
                    0.17427006363868713
                ],
                [
                    0.0,
                    0.0,
                    0.0,
                    1.0
                ]
            ]
        },
        {
            "file_path": "/data/shapenet_blender/all_50_random/02958343/cc7f51159a1a12fea7fd25564c2e888e/r_8",
            "rotation": 0.12566370614359174,
            "transform_matrix": [
                [
                    0.7308560013771057,
                    0.009644551202654839,
                    0.6824635863304138,
                    2.7510986328125
                ],
                [
                    0.6825317740440369,
                    -0.010327400639653206,
                    -0.7307829856872559,
                    -2.94588041305542
                ],
                [
                    9.313225746154785e-10,
                    0.9999001622200012,
                    -0.014130555093288422,
                    -0.056962087750434875
                ],
                [
                    0.0,
                    0.0,
                    0.0,
                    1.0
                ]
            ]
        },
        {
            "file_path": "/data/shapenet_blender/all_50_random/02958343/cc7f51159a1a12fea7fd25564c2e888e/r_9",
            "rotation": 0.12566370614359174,
            "transform_matrix": [
                [
                    0.8961408734321594,
                    -0.009032602421939373,
                    -0.4436779022216797,
                    -1.7885228395462036
                ],
                [
                    -0.4437699019908905,
                    -0.018240271136164665,
                    -0.8959550857543945,
                    -3.611710548400879
                ],
                [
                    9.31322685637781e-10,
                    0.9997928142547607,
                    -0.020354248583316803,
                    -0.08205059915781021
                ],
                [
                    0.0,
                    0.0,
                    0.0,
                    1.0
                ]
            ]
        },
        {
            "file_path": "/data/shapenet_blender/all_50_random/02958343/cc7f51159a1a12fea7fd25564c2e888e/r_10",
            "rotation": 0.12566370614359174,
            "transform_matrix": [
                [
                    0.18643459677696228,
                    0.13406360149383545,
                    -0.9732775092124939,
                    -3.9234070777893066
                ],
                [
                    -0.9824674129486084,
                    0.025440124794840813,
                    -0.1846907138824463,
                    -0.7445120811462402
                ],
                [
                    0.0,
                    0.9906461238861084,
                    0.13645602762699127,
                    0.5500718355178833
                ],
                [
                    0.0,
                    0.0,
                    0.0,
                    1.0
                ]
            ]
        },
        {
            "file_path": "/data/shapenet_blender/all_50_random/02958343/cc7f51159a1a12fea7fd25564c2e888e/r_11",
            "rotation": 0.12566370614359174,
            "transform_matrix": [
                [
                    -0.6440540552139282,
                    0.35225823521614075,
                    -0.6790496706962585,
                    -2.7373368740081787
                ],
                [
                    -0.7649800777435303,
                    -0.296574205160141,
                    0.5717073678970337,
                    2.304626226425171
                ],
                [
                    0.0,
                    0.8876698613166809,
                    0.46048030257225037,
                    1.8562555313110352
                ],
                [
                    0.0,
                    0.0,
                    0.0,
                    1.0
                ]
            ]
        },
        {
            "file_path": "/data/shapenet_blender/all_50_random/02958343/cc7f51159a1a12fea7fd25564c2e888e/r_12",
            "rotation": 0.12566370614359174,
            "transform_matrix": [
                [
                    0.9893728494644165,
                    -0.005851186346262693,
                    0.1452822983264923,
                    0.5856517553329468
                ],
                [
                    0.14540007710456848,
                    0.03981431573629379,
                    -0.9885714650154114,
                    -3.9850592613220215
                ],
                [
                    0.0,
                    0.9991900324821472,
                    0.04024196416139603,
                    0.1622205674648285
                ],
                [
                    0.0,
                    0.0,
                    0.0,
                    1.0
                ]
            ]
        },
        {
            "file_path": "/data/shapenet_blender/all_50_random/02958343/cc7f51159a1a12fea7fd25564c2e888e/r_13",
            "rotation": 0.12566370614359174,
            "transform_matrix": [
                [
                    0.9505147933959961,
                    0.048346299678087234,
                    -0.3068946897983551,
                    -1.23713219165802
                ],
                [
                    -0.31067946553230286,
                    0.1479140967130661,
                    -0.9389352798461914,
                    -3.7849695682525635
                ],
                [
                    3.725290298461914e-09,
                    0.9878178834915161,
                    0.1556147038936615,
                    0.6273030042648315
                ],
                [
                    0.0,
                    0.0,
                    0.0,
                    1.0
                ]
            ]
        },
        {
            "file_path": "/data/shapenet_blender/all_50_random/02958343/cc7f51159a1a12fea7fd25564c2e888e/r_14",
            "rotation": 0.12566370614359174,
            "transform_matrix": [
                [
                    -0.9522377848625183,
                    -0.29420244693756104,
                    -0.08178171515464783,
                    -0.329672634601593
                ],
                [
                    -0.3053577244281769,
                    0.9174507856369019,
                    0.2550308406352997,
                    1.0280622243881226
                ],
                [
                    0.0,
                    0.2678225338459015,
                    -0.9634682536125183,
                    -3.883864641189575
                ],
                [
                    0.0,
                    0.0,
                    0.0,
                    1.0
                ]
            ]
        },
        {
            "file_path": "/data/shapenet_blender/all_50_random/02958343/cc7f51159a1a12fea7fd25564c2e888e/r_15",
            "rotation": 0.12566370614359174,
            "transform_matrix": [
                [
                    -0.2849167287349701,
                    -0.24231749773025513,
                    0.9274182915687561,
                    3.7385427951812744
                ],
                [
                    0.9585523009300232,
                    -0.0720255970954895,
                    0.2756625711917877,
                    1.1112313270568848
                ],
                [
                    -7.450580596923828e-09,
                    0.9675197601318359,
                    0.2527952790260315,
                    1.0190503597259521
                ],
                [
                    0.0,
                    0.0,
                    0.0,
                    1.0
                ]
            ]
        },
        {
            "file_path": "/data/shapenet_blender/all_50_random/02958343/cc7f51159a1a12fea7fd25564c2e888e/r_16",
            "rotation": 0.12566370614359174,
            "transform_matrix": [
                [
                    -0.9895144104957581,
                    0.13710281252861023,
                    0.045433513820171356,
                    0.1831483542919159
                ],
                [
                    0.14443472027778625,
                    0.9392839074134827,
                    0.3112625181674957,
                    1.2547394037246704
                ],
                [
                    -3.725290742551124e-09,
                    0.31456080079078674,
                    -0.9492372870445251,
                    -3.826497793197632
                ],
                [
                    0.0,
                    0.0,
                    0.0,
                    1.0
                ]
            ]
        },
        {
            "file_path": "/data/shapenet_blender/all_50_random/02958343/cc7f51159a1a12fea7fd25564c2e888e/r_17",
            "rotation": 0.12566370614359174,
            "transform_matrix": [
                [
                    0.38310506939888,
                    0.16888301074504852,
                    -0.908134937286377,
                    -3.66080904006958
                ],
                [
                    -0.9237047433853149,
                    0.07004396617412567,
                    -0.3766475319862366,
                    -1.5183147192001343
                ],
                [
                    0.0,
                    0.9831441044807434,
                    0.1828322559595108,
                    0.7370203733444214
                ],
                [
                    0.0,
                    0.0,
                    0.0,
                    1.0
                ]
            ]
        },
        {
            "file_path": "/data/shapenet_blender/all_50_random/02958343/cc7f51159a1a12fea7fd25564c2e888e/r_18",
            "rotation": 0.12566370614359174,
            "transform_matrix": [
                [
                    0.11989903450012207,
                    0.31277555227279663,
                    -0.9422290325164795,
                    -3.7982468605041504
                ],
                [
                    -0.9927861094474792,
                    0.0377739854156971,
                    -0.11379324644804001,
                    -0.4587152898311615
                ],
                [
                    0.0,
                    0.9490756392478943,
                    0.3150482475757599,
                    1.2700002193450928
                ],
                [
                    0.0,
                    0.0,
                    0.0,
                    1.0
                ]
            ]
        },
        {
            "file_path": "/data/shapenet_blender/all_50_random/02958343/cc7f51159a1a12fea7fd25564c2e888e/r_19",
            "rotation": 0.12566370614359174,
            "transform_matrix": [
                [
                    -0.9397143721580505,
                    -0.11257457733154297,
                    -0.32289889454841614,
                    -1.3016470670700073
                ],
                [
                    -0.3419601321220398,
                    0.30935758352279663,
                    0.8873337507247925,
                    3.5769565105438232
                ],
                [
                    0.0,
                    0.9442588686943054,
                    -0.3292037844657898,
                    -1.3270628452301025
                ],
                [
                    0.0,
                    0.0,
                    0.0,
                    1.0
                ]
            ]
        },
        {
            "file_path": "/data/shapenet_blender/all_50_random/02958343/cc7f51159a1a12fea7fd25564c2e888e/r_20",
            "rotation": 0.12566370614359174,
            "transform_matrix": [
                [
                    0.7524262070655823,
                    0.0788102000951767,
                    -0.6539449095726013,
                    -2.6361358165740967
                ],
                [
                    -0.6586766839027405,
                    0.09002727270126343,
                    -0.747020959854126,
                    -3.0113375186920166
                ],
                [
                    3.725290298461914e-09,
                    0.992816150188446,
                    0.11964933574199677,
                    0.4823218286037445
                ],
                [
                    0.0,
                    0.0,
                    0.0,
                    1.0
                ]
            ]
        },
        {
            "file_path": "/data/shapenet_blender/all_50_random/02958343/cc7f51159a1a12fea7fd25564c2e888e/r_21",
            "rotation": 0.12566370614359174,
            "transform_matrix": [
                [
                    0.920818030834198,
                    -0.2476108819246292,
                    -0.30130231380462646,
                    -1.2145885229110718
                ],
                [
                    -0.3899926543235779,
                    -0.5846380591392517,
                    -0.7114098072052002,
                    -2.8677847385406494
                ],
                [
                    0.0,
                    0.7725846171379089,
                    -0.6349117159843445,
                    -2.55941104888916
                ],
                [
                    0.0,
                    0.0,
                    0.0,
                    1.0
                ]
            ]
        },
        {
            "file_path": "/data/shapenet_blender/all_50_random/02958343/cc7f51159a1a12fea7fd25564c2e888e/r_22",
            "rotation": 0.12566370614359174,
            "transform_matrix": [
                [
                    0.986788272857666,
                    -0.10027797520160675,
                    -0.12725329399108887,
                    -0.5129745006561279
                ],
                [
                    -0.16201567649841309,
                    -0.6107627153396606,
                    -0.7750611901283264,
                    -3.1243717670440674
                ],
                [
                    0.0,
                    0.7854382991790771,
                    -0.6189399361610413,
                    -2.4950268268585205
                ],
                [
                    0.0,
                    0.0,
                    0.0,
                    1.0
                ]
            ]
        },
        {
            "file_path": "/data/shapenet_blender/all_50_random/02958343/cc7f51159a1a12fea7fd25564c2e888e/r_23",
            "rotation": 0.12566370614359174,
            "transform_matrix": [
                [
                    0.9372932314872742,
                    0.21763330698013306,
                    -0.27224448323249817,
                    -1.0974527597427368
                ],
                [
                    -0.3485417068004608,
                    0.5852562189102173,
                    -0.7321158051490784,
                    -2.9512534141540527
                ],
                [
                    0.0,
                    0.7810958623886108,
                    0.6244109869003296,
                    2.5170814990997314
                ],
                [
                    0.0,
                    0.0,
                    0.0,
                    1.0
                ]
            ]
        },
        {
            "file_path": "/data/shapenet_blender/all_50_random/02958343/cc7f51159a1a12fea7fd25564c2e888e/r_24",
            "rotation": 0.12566370614359174,
            "transform_matrix": [
                [
                    0.9777681231498718,
                    0.09546946734189987,
                    0.18669529259204865,
                    0.7525928020477295
                ],
                [
                    0.2096892148256302,
                    -0.4451684057712555,
                    -0.8705489635467529,
                    -3.5092952251434326
                ],
                [
                    0.0,
                    0.8903429508209229,
                    -0.45529040694236755,
                    -1.835334300994873
                ],
                [
                    0.0,
                    0.0,
                    0.0,
                    1.0
                ]
            ]
        },
        {
            "file_path": "/data/shapenet_blender/all_50_random/02958343/cc7f51159a1a12fea7fd25564c2e888e/r_25",
            "rotation": 0.12566370614359174,
            "transform_matrix": [
                [
                    -0.8041430115699768,
                    0.22879737615585327,
                    0.5486398935317993,
                    2.2116382122039795
                ],
                [
                    0.5944358110427856,
                    0.30951330065727234,
                    0.7421910166740417,
                    2.991867780685425
                ],
                [
                    0.0,
                    0.9229589700698853,
                    -0.3848983347415924,
                    -1.5515748262405396
                ],
                [
                    0.0,
                    0.0,
                    0.0,
                    1.0
                ]
            ]
        },
        {
            "file_path": "/data/shapenet_blender/all_50_random/02958343/cc7f51159a1a12fea7fd25564c2e888e/r_26",
            "rotation": 0.12566370614359174,
            "transform_matrix": [
                [
                    -0.949809730052948,
                    -0.04790956899523735,
                    0.309137761592865,
                    1.2461740970611572
                ],
                [
                    0.3128281831741333,
                    -0.14546313881874084,
                    0.9386048316955566,
                    3.7836368083953857
                ],
                [
                    0.0,
                    0.9882028698921204,
                    0.1531497687101364,
                    0.6173664331436157
                ],
                [
                    0.0,
                    0.0,
                    0.0,
                    1.0
                ]
            ]
        },
        {
            "file_path": "/data/shapenet_blender/all_50_random/02958343/cc7f51159a1a12fea7fd25564c2e888e/r_27",
            "rotation": 0.12566370614359174,
            "transform_matrix": [
                [
                    0.22077986598014832,
                    -0.6368412971496582,
                    -0.7387077808380127,
                    -2.9778265953063965
                ],
                [
                    -0.9753236770629883,
                    -0.14415906369686127,
                    -0.1672181338071823,
                    -0.6740779280662537
                ],
                [
                    -7.450580596923828e-09,
                    0.7573975324630737,
                    -0.6529538631439209,
                    -2.632141351699829
                ],
                [
                    0.0,
                    0.0,
                    0.0,
                    1.0
                ]
            ]
        },
        {
            "file_path": "/data/shapenet_blender/all_50_random/02958343/cc7f51159a1a12fea7fd25564c2e888e/r_28",
            "rotation": 0.12566370614359174,
            "transform_matrix": [
                [
                    0.43587782979011536,
                    -0.1624515801668167,
                    -0.8852230906486511,
                    -3.568448543548584
                ],
                [
                    -0.9000059366226196,
                    -0.07867619395256042,
                    -0.4287184178829193,
                    -1.7282193899154663
                ],
                [
                    0.0,
                    0.9835748076438904,
                    -0.1805005669593811,
                    -0.7276211380958557
                ],
                [
                    0.0,
                    0.0,
                    0.0,
                    1.0
                ]
            ]
        },
        {
            "file_path": "/data/shapenet_blender/all_50_random/02958343/cc7f51159a1a12fea7fd25564c2e888e/r_29",
            "rotation": 0.12566370614359174,
            "transform_matrix": [
                [
                    -0.1061553880572319,
                    -0.04324042797088623,
                    0.9934089183807373,
                    4.004559516906738
                ],
                [
                    0.9943495988845825,
                    -0.004616288468241692,
                    0.10605496913194656,
                    0.4275212585926056
                ],
                [
                    0.0,
                    0.9990540742874146,
                    0.04348614066839218,
                    0.17529824376106262
                ],
                [
                    0.0,
                    0.0,
                    0.0,
                    1.0
                ]
            ]
        },
        {
            "file_path": "/data/shapenet_blender/all_50_random/02958343/cc7f51159a1a12fea7fd25564c2e888e/r_30",
            "rotation": 0.12566370614359174,
            "transform_matrix": [
                [
                    -0.9311612844467163,
                    -0.2813827097415924,
                    -0.2318674623966217,
                    -0.934687614440918
                ],
                [
                    -0.36460772156715393,
                    0.7186152935028076,
                    0.5921597480773926,
                    2.3870723247528076
                ],
                [
                    -1.4901162970204496e-08,
                    0.6359367966651917,
                    -0.7717410922050476,
                    -3.110987901687622
                ],
                [
                    0.0,
                    0.0,
                    0.0,
                    1.0
                ]
            ]
        },
        {
            "file_path": "/data/shapenet_blender/all_50_random/02958343/cc7f51159a1a12fea7fd25564c2e888e/r_31",
            "rotation": 0.12566370614359174,
            "transform_matrix": [
                [
                    -0.8439162373542786,
                    0.1778295785188675,
                    0.5061442852020264,
                    2.040332794189453
                ],
                [
                    0.5364749431610107,
                    0.2797395586967468,
                    0.7962036728858948,
                    3.209599733352661
                ],
                [
                    -2.9802322387695312e-08,
                    0.9434629082679749,
                    -0.3314778804779053,
                    -1.3362300395965576
                ],
                [
                    0.0,
                    0.0,
                    0.0,
                    1.0
                ]
            ]
        },
        {
            "file_path": "/data/shapenet_blender/all_50_random/02958343/cc7f51159a1a12fea7fd25564c2e888e/r_32",
            "rotation": 0.12566370614359174,
            "transform_matrix": [
                [
                    0.6661997437477112,
                    -0.16187222301959991,
                    0.7279940247535706,
                    2.9346377849578857
                ],
                [
                    0.745773434638977,
                    0.14460055530071259,
                    -0.6503174304962158,
                    -2.6215133666992188
                ],
                [
                    -1.4901161193847656e-08,
                    0.9761598110198975,
                    0.21705284714698792,
                    0.8749679923057556
                ],
                [
                    0.0,
                    0.0,
                    0.0,
                    1.0
                ]
            ]
        },
        {
            "file_path": "/data/shapenet_blender/all_50_random/02958343/cc7f51159a1a12fea7fd25564c2e888e/r_33",
            "rotation": 0.12566370614359174,
            "transform_matrix": [
                [
                    -0.9963136911392212,
                    -0.04846629872918129,
                    0.07078243046998978,
                    0.2853330969810486
                ],
                [
                    0.0857853963971138,
                    -0.5628887414932251,
                    0.8220688104629517,
                    3.3138654232025146
                ],
                [
                    0.0,
                    0.8251104354858398,
                    0.564971387386322,
                    2.277472496032715
                ],
                [
                    0.0,
                    0.0,
                    0.0,
                    1.0
                ]
            ]
        },
        {
            "file_path": "/data/shapenet_blender/all_50_random/02958343/cc7f51159a1a12fea7fd25564c2e888e/r_34",
            "rotation": 0.12566370614359174,
            "transform_matrix": [
                [
                    0.21464364230632782,
                    -0.04710618406534195,
                    0.9755557179450989,
                    3.932591199874878
                ],
                [
                    0.9766923785209656,
                    0.010352331213653088,
                    -0.21439383924007416,
                    -0.8642492890357971
                ],
                [
                    -9.313225191043273e-10,
                    0.9988362193107605,
                    0.04823031648993492,
                    0.1944226324558258
                ],
                [
                    0.0,
                    0.0,
                    0.0,
                    1.0
                ]
            ]
        },
        {
            "file_path": "/data/shapenet_blender/all_50_random/02958343/cc7f51159a1a12fea7fd25564c2e888e/r_35",
            "rotation": 0.12566370614359174,
            "transform_matrix": [
                [
                    0.5394781827926636,
                    -0.07328593730926514,
                    0.8388041257858276,
                    3.3813278675079346
                ],
                [
                    0.8419996500015259,
                    0.046955086290836334,
                    -0.5374307632446289,
                    -2.1664528846740723
                ],
                [
                    0.0,
                    0.9962049722671509,
                    0.08703796565532684,
                    0.3508612811565399
                ],
                [
                    0.0,
                    0.0,
                    0.0,
                    1.0
                ]
            ]
        },
        {
            "file_path": "/data/shapenet_blender/all_50_random/02958343/cc7f51159a1a12fea7fd25564c2e888e/r_36",
            "rotation": 0.12566370614359174,
            "transform_matrix": [
                [
                    -0.9523776769638062,
                    0.0037187833804637194,
                    -0.30489811301231384,
                    -1.229083776473999
                ],
                [
                    -0.30492082238197327,
                    -0.011615102179348469,
                    0.9523068070411682,
                    3.838871717453003
                ],
                [
                    -2.3283062977608182e-10,
                    0.9999256134033203,
                    0.012195897288620472,
                    0.04916323721408844
                ],
                [
                    0.0,
                    0.0,
                    0.0,
                    1.0
                ]
            ]
        },
        {
            "file_path": "/data/shapenet_blender/all_50_random/02958343/cc7f51159a1a12fea7fd25564c2e888e/r_37",
            "rotation": 0.12566370614359174,
            "transform_matrix": [
                [
                    0.043994564563035965,
                    0.34044238924980164,
                    -0.9392355680465698,
                    -3.786179542541504
                ],
                [
                    -0.9990317225456238,
                    0.014992130920290947,
                    -0.041361309587955475,
                    -0.1667327731847763
                ],
                [
                    -9.313224080820248e-10,
                    0.9401459097862244,
                    0.3407723009586334,
                    1.37369704246521
                ],
                [
                    0.0,
                    0.0,
                    0.0,
                    1.0
                ]
            ]
        },
        {
            "file_path": "/data/shapenet_blender/all_50_random/02958343/cc7f51159a1a12fea7fd25564c2e888e/r_38",
            "rotation": 0.12566370614359174,
            "transform_matrix": [
                [
                    0.9992942214012146,
                    0.002793189836665988,
                    0.03746138513088226,
                    0.15101167559623718
                ],
                [
                    0.03756537660956383,
                    -0.07430295646190643,
                    -0.996527910232544,
                    -4.01713228225708
                ],
                [
                    2.3283064365386963e-10,
                    0.9972318410873413,
                    -0.07435542345046997,
                    -0.29973629117012024
                ],
                [
                    0.0,
                    0.0,
                    0.0,
                    1.0
                ]
            ]
        },
        {
            "file_path": "/data/shapenet_blender/all_50_random/02958343/cc7f51159a1a12fea7fd25564c2e888e/r_39",
            "rotation": 0.12566370614359174,
            "transform_matrix": [
                [
                    0.23976412415504456,
                    -0.5469151735305786,
                    -0.8021203279495239,
                    -3.233450412750244
                ],
                [
                    -0.9708312153816223,
                    -0.13507047295570374,
                    -0.19809794425964355,
                    -0.7985583543777466
                ],
                [
                    0.0,
                    0.8262202143669128,
                    -0.563347339630127,
                    -2.270925760269165
                ],
                [
                    0.0,
                    0.0,
                    0.0,
                    1.0
                ]
            ]
        },
        {
            "file_path": "/data/shapenet_blender/all_50_random/02958343/cc7f51159a1a12fea7fd25564c2e888e/r_40",
            "rotation": 0.12566370614359174,
            "transform_matrix": [
                [
                    -0.9447344541549683,
                    0.18375764787197113,
                    0.2714957594871521,
                    1.094434380531311
                ],
                [
                    0.3278365731239319,
                    0.5295388102531433,
                    0.7823758125305176,
                    3.153857707977295
                ],
                [
                    0.0,
                    0.8281435370445251,
                    -0.5605160593986511,
                    -2.259512424468994
                ],
                [
                    0.0,
                    0.0,
                    0.0,
                    1.0
                ]
            ]
        },
        {
            "file_path": "/data/shapenet_blender/all_50_random/02958343/cc7f51159a1a12fea7fd25564c2e888e/r_41",
            "rotation": 0.12566370614359174,
            "transform_matrix": [
                [
                    0.9195663928985596,
                    -0.07982931286096573,
                    0.3847401440143585,
                    1.5509371757507324
                ],
                [
                    0.39293473958969116,
                    0.18682073056697845,
                    -0.9003889560699463,
                    -3.6295840740203857
                ],
                [
                    -7.450580596923828e-09,
                    0.9791451096534729,
                    0.2031617909669876,
                    0.8189713954925537
                ],
                [
                    0.0,
                    0.0,
                    0.0,
                    1.0
                ]
            ]
        },
        {
            "file_path": "/data/shapenet_blender/all_50_random/02958343/cc7f51159a1a12fea7fd25564c2e888e/r_42",
            "rotation": 0.12566370614359174,
            "transform_matrix": [
                [
                    0.9840612411499023,
                    0.08199166506528854,
                    0.15780037641525269,
                    0.6361136436462402
                ],
                [
                    0.1778302639722824,
                    -0.4537181854248047,
                    -0.8732216954231262,
                    -3.5200693607330322
                ],
                [
                    0.0,
                    0.8873652815818787,
                    -0.4610670208930969,
                    -1.8586206436157227
                ],
                [
                    0.0,
                    0.0,
                    0.0,
                    1.0
                ]
            ]
        },
        {
            "file_path": "/data/shapenet_blender/all_50_random/02958343/cc7f51159a1a12fea7fd25564c2e888e/r_43",
            "rotation": 0.12566370614359174,
            "transform_matrix": [
                [
                    -0.9252249002456665,
                    0.016917424276471138,
                    0.3790416419506073,
                    1.527965784072876
                ],
                [
                    0.3794189393520355,
                    0.04125365987420082,
                    0.9243047833442688,
                    3.725991725921631
                ],
                [
                    0.0,
                    0.9990054965019226,
                    -0.04458770900964737,
                    -0.17973880469799042
                ],
                [
                    0.0,
                    0.0,
                    0.0,
                    1.0
                ]
            ]
        },
        {
            "file_path": "/data/shapenet_blender/all_50_random/02958343/cc7f51159a1a12fea7fd25564c2e888e/r_44",
            "rotation": 0.12566370614359174,
            "transform_matrix": [
                [
                    -0.18755388259887695,
                    -0.703901469707489,
                    0.6850884556770325,
                    2.7616798877716064
                ],
                [
                    0.9822543859481812,
                    -0.13440454006195068,
                    0.13081234693527222,
                    0.527321457862854
                ],
                [
                    -7.450581485102248e-09,
                    0.6974654197692871,
                    0.7166183590888977,
                    2.8887810707092285
                ],
                [
                    0.0,
                    0.0,
                    0.0,
                    1.0
                ]
            ]
        },
        {
            "file_path": "/data/shapenet_blender/all_50_random/02958343/cc7f51159a1a12fea7fd25564c2e888e/r_45",
            "rotation": 0.12566370614359174,
            "transform_matrix": [
                [
                    0.5623698234558105,
                    0.4448968470096588,
                    0.6969985365867615,
                    2.8096909523010254
                ],
                [
                    0.8268858194351196,
                    -0.30257686972618103,
                    -0.4740327298641205,
                    -1.9108870029449463
                ],
                [
                    -2.9802322387695312e-08,
                    0.8429198861122131,
                    -0.5380390286445618,
                    -2.1689047813415527
                ],
                [
                    0.0,
                    0.0,
                    0.0,
                    1.0
                ]
            ]
        },
        {
            "file_path": "/data/shapenet_blender/all_50_random/02958343/cc7f51159a1a12fea7fd25564c2e888e/r_46",
            "rotation": 0.12566370614359174,
            "transform_matrix": [
                [
                    -0.7630707621574402,
                    0.28965726494789124,
                    0.5777729153633118,
                    2.3290772438049316
                ],
                [
                    0.6463149189949036,
                    0.34198349714279175,
                    0.6821468472480774,
                    2.7498221397399902
                ],
                [
                    -1.4901159417490817e-08,
                    0.8939496278762817,
                    -0.4481674134731293,
                    -1.806620717048645
                ],
                [
                    0.0,
                    0.0,
                    0.0,
                    1.0
                ]
            ]
        },
        {
            "file_path": "/data/shapenet_blender/all_50_random/02958343/cc7f51159a1a12fea7fd25564c2e888e/r_47",
            "rotation": 0.12566370614359174,
            "transform_matrix": [
                [
                    0.6531442403793335,
                    0.471646249294281,
                    -0.5924123525619507,
                    -2.3880906105041504
                ],
                [
                    -0.7572336196899414,
                    0.40681374073028564,
                    -0.5109793543815613,
                    -2.059823751449585
                ],
                [
                    -1.4901162970204496e-08,
                    0.7823376655578613,
                    0.6228544116020203,
                    2.5108065605163574
                ],
                [
                    0.0,
                    0.0,
                    0.0,
                    1.0
                ]
            ]
        },
        {
            "file_path": "/data/shapenet_blender/all_50_random/02958343/cc7f51159a1a12fea7fd25564c2e888e/r_48",
            "rotation": 0.12566370614359174,
            "transform_matrix": [
                [
                    0.7005937099456787,
                    -0.11201048642396927,
                    -0.7047141790390015,
                    -2.8407938480377197
                ],
                [
                    -0.7135604619979858,
                    -0.10997504740953445,
                    -0.6919081807136536,
                    -2.7891712188720703
                ],
                [
                    -7.450580596923828e-09,
                    0.987602710723877,
                    -0.15697407722473145,
                    -0.6327828168869019
                ],
                [
                    0.0,
                    0.0,
                    0.0,
                    1.0
                ]
            ]
        },
        {
            "file_path": "/data/shapenet_blender/all_50_random/02958343/cc7f51159a1a12fea7fd25564c2e888e/r_49",
            "rotation": 0.12566370614359174,
            "transform_matrix": [
                [
                    -0.920267641544342,
                    0.3498480021953583,
                    0.1752534806728363,
                    0.7064693570137024
                ],
                [
                    0.3912894129753113,
                    0.8228022456169128,
                    0.4121760129928589,
                    1.6615346670150757
                ],
                [
                    0.0,
                    0.44788703322410583,
                    -0.8940901160240173,
                    -3.6041924953460693
                ],
                [
                    0.0,
                    0.0,
                    0.0,
                    1.0
                ]
            ]
        }
    ]
}